rospkg/__init__.py
rospkg/common.py
rospkg/distro.py
rospkg/environment.py
rospkg/manifest.py
rospkg/os_detect.py
rospkg/rospack.py
rospkg/rosversion.py
rospkg/stack.py
rospkg-1.6.1.dist-info/METADATA
rospkg-1.6.1.dist-info/WHEEL
rospkg-1.6.1.dist-info/entry_points.txt
rospkg-1.6.1.dist-info/top_level.txt
rospkg-1.6.1.dist-info/RECORD
